finlab_crypto/__init__.py
finlab_crypto/chart.py
finlab_crypto/crawler.py
finlab_crypto/indicators.py
finlab_crypto/online.py
finlab_crypto/overfitting.py
finlab_crypto/strategy.py
finlab_crypto/talib_filter.py
finlab_crypto/talib_strategy.py
finlab_crypto/utility.py
finlab_crypto-0.2.27.dist-info/LICENSE
finlab_crypto-0.2.27.dist-info/METADATA
finlab_crypto-0.2.27.dist-info/WHEEL
finlab_crypto-0.2.27.dist-info/top_level.txt
finlab_crypto-0.2.27.dist-info/RECORD
