Metadata-Version: 2.1
Name: finlab-crypto
Version: 0.2.27
Summary: A backtesting framework for crytpo currency
Author: FinLab
Author-email: finlabstaff@gmail.com
Classifier: Programming Language :: Python :: 3
Classifier: Programming Language :: Python :: 3.4
Classifier: Programming Language :: Python :: 3.5
Classifier: Programming Language :: Python :: 3.6
Classifier: Programming Language :: Python :: 3.7
Classifier: Programming Language :: Python :: 3.8
Classifier: License :: OSI Approved :: GNU General Public License v3 (GPLv3)
Classifier: Operating System :: OS Independent
Requires-Python: >=3
License-File: LICENSE
Requires-Dist: numba (>=0.53.1)
Requires-Dist: pandas (>=1.1.5)
Requires-Dist: python-binance (>=0.7.5)
Requires-Dist: pyecharts (==1.9.1)
Requires-Dist: vectorbt
Requires-Dist: statsmodels (>=0.10.2)
Requires-Dist: tqdm (>=4.41.1)
Requires-Dist: seaborn (>=0.10.1)
